meco/__init__.py
meco/_version.py
meco/meco.py
test/__init__.py
test/test_eco.py
meco-1.0.1.dist-info/LICENSE.txt
meco-1.0.1.dist-info/METADATA
meco-1.0.1.dist-info/WHEEL
meco-1.0.1.dist-info/top_level.txt
meco-1.0.1.dist-info/RECORD
